Workbook

Sheet Cover Page
A2: DETAILED PROJECT REPORT FOR
A3: Malan Food Products Pvt Ltd
A10: Address :
A11: Rudreswar, Parbatkash
A12: North Guwahati
A13: Guwahati-781030
A22: This project has been designed to establish a Bakery. It is a Private Limited Company . The Company having experience in this line of business. Now it is proposed to start operation with financial assistance from a suitable commercial bank.
A23: Hence this project Report is presented.

Sheet Index
A2: ='Cover Page'!A3 -> Malan Food Products Pvt Ltd
B4: I N D E X
A5: SL. | B5: C O N T E N T S | C5: PAGES
B7: CHAPTER :
A8: 1 | B8: PROJECT AT GLANCE | C8: 1
A9: 2 | B9: FEASIBILITY REPORT | C9: 2
A10: 3 | B10: COST OF THE PROJECT AND MEANS OF FINANCE | C10: 3
A11: 4 | B11: PROJECTIONS AND PROFITABILITY STATEMENT | C11: 4
A12: 5 | B12: BALANCE SHEET | C12: 5
A13: 6 | B13: CASH FLOW | C13: 6
B15: A N N E X U R E S
A16: 1 | B16: DEPRECIATION SCHEDULE | C16: 7
A17: 2 | B17: CAPITAL ACCOUNT | C17: 8
A18: 3 | B18: BREAK EVEN ANALYSIS | C18: 9
A19: 4 | B19: RETURN ON CAPITAL EMPLOYED | C19: 10
A20: 5 | B20: DEBT SERVICE COVERAGE RATIO | C20: 11
A21: 6 | B21: FIXED ASSET COVERAGE RATIO | C21: 12
A22: 7 | B22: CURRENT RATIO | C22: 13
A23: 8 | B23: QUICK RATIO | C23: 14
A24: 9 | B24: TOL/TNW | C24: 15
A25: 10 | B25: DEBT EQUITY RATIO | C25: 16
A26: 11 | B26: SALARY STETEMENT | C26: 17
A27: 12 | B27: CURRENT ASSETS CHART | C27: 18
... A29: 14 | B29: SALES PIVOT CHART | C29: 20
A30: 15 | B30: LOAN INSTALLMENT STATEMENT | C30: 21-22

Sheet PROJECT AT GLANCE
A1: =Index!A2 -> Malan Food Products Pvt Ltd
A2: CHAPTER NO. 1
A3: PROJECT AT GLANCE :
A4: 1 | B4: Name | C4: : | D4: ='Cover Page'!A3 -> Malan Food Products Pvt Ltd
A5: 2 | B5: Address | C5: : | D5: Reg.Office:
D6: ='Cover Page'!A11 -> Rudreswar, Parbatkash
D7: ='Cover Page'!A12 -> North Guwahati
D8: ='Cover Page'!A13 -> Guwahati-781030
A11: 3 | B11: Nature of Business | C11: : | D11: Bakery
A14: 5 | B14: Cost of the project | C14: : | E14: (Rs.)
B15: Particulars | E15: Total
B16: Stock Purchase | E16: 0
B17: Construction | E17: 0
B18: Machinery & Equipments | E18: 0
B19: Total | E19: =SUM(E16:E18) -> 0
B21: Means of Finance | C21: :
B22: Particulars | E22: Total
B23: Proprietor Contribution | E23: =E27-E25-E24 -> 0
B24: Term Loan from Bank / Institution | E24: 0
B25: Cash Credit | E25: 0
B27: Total | E27: =E19 -> 0
E29: Year 1
A30: 6 | B30: Debt Service Coverage Ratio | C30: : | E30: =DSCR!B20 -> #DIV/0!
A31: 7 | B31: Current ratio | C31: : | E31: ='Current Ratio'!B20 -> #DIV/0!
A32: 8 | B32: TOL/TNW | C32: : | E32: ='TOL TNW'!B19 -> #DIV/0!
A33: 9 | B33: Debt Equity Ratio | C33: : | E33: ='DEBT EQUITY'!B19 -> #DIV/0!
A34: 10 | B34: Net Profit Rate | C34: : | E34: =profit!B31*100/profit!B7 -> #DIV/0!
A35: 11 | B35: Monthly Instalment | C35: : | E35: Rs. 70600.00
A36: 12 | B36: Monthly Income | E36: Rs. 251500.00

Sheet FEASIBILITY REPORT
A1: =DSCR!A1 -> Malan Food Products Pvt Ltd
A2: ANNEXURE NO.
A4: PROJECT FEASIBILITY REPORT
A6: Particulars | B6: Operating Years
B7: 1 | C7: 2 | D7: 3 | E7: 4 | F7: 5 | G7: 6 | H7: 7
A9: Current Ratio | B9: ='Current Ratio'!B20 -> #DIV/0! | C9: ='Current Ratio'!C20 -> #DIV/0! | D9: ='Current Ratio'!D20 -> #DIV/0! | E9: ='Current Ratio'!E20 -> #DIV/0! | F9: ='Current Ratio'!F20 -> #DIV/0! | G9: ='Current Ratio'!G20 -> #DIV/0! | H9: ='Current Ratio'!H20 -> #DIV/0!
A11: Quick Ratio | B11: ='Quick ratio'!B19 -> #DIV/0! | C11: ='Quick ratio'!C19 -> #DIV/0! | D11: ='Quick ratio'!D19 -> #DIV/0! | E11: ='Quick ratio'!E19 -> #DIV/0! | F11: ='Quick ratio'!F19 -> #DIV/0! | G11: ='Quick ratio'!G19 -> #DIV/0! | H11: ='Quick ratio'!H19 -> #DIV/0!
A13: Debt Service Coverage Ratio | B13: =DSCR!B20 -> #DIV/0! | C13: =DSCR!C20 -> #DIV/0! | D13: =DSCR!D20 -> #DIV/0! | E13: =DSCR!E20 -> #DIV/0! | F13: =DSCR!F20 -> #DIV/0! | G13: =DSCR!G20 -> #DIV/0! | H13: =DSCR!H20 -> #DIV/0!
A15: TOL/TNW | B15: ='TOL TNW'!B19 -> #DIV/0! | C15: ='TOL TNW'!C19 -> #DIV/0! | D15: ='TOL TNW'!D19 -> #DIV/0! | E15: ='TOL TNW'!E19 -> #DIV/0! | F15: ='TOL TNW'!F19 -> #DIV/0! | G15: ='TOL TNW'!G19 -> #DIV/0! | H15: ='TOL TNW'!H19 -> #DIV/0!
A17: Debt Equity Ratio | B17: ='DEBT EQUITY'!B19 -> #DIV/0! | C17: ='DEBT EQUITY'!C19 -> #DIV/0! | D17: ='DEBT EQUITY'!D19 -> #DIV/0! | E17: ='DEBT EQUITY'!E19 -> #DIV/0! | F17: ='DEBT EQUITY'!F19 -> #DIV/0! | G17: ='DEBT EQUITY'!G19 -> #DIV/0! | H17: ='DEBT EQUITY'!H19 -> #DIV/0!
A19: Net Profit Sales Percentage | B19: =profit!B31*100/profit!B7 -> #DIV/0! | C19: =profit!C31*100/profit!C7 -> #DIV/0! | D19: =profit!D31*100/profit!D7 -> #DIV/0! | E19: =profit!E31*100/profit!E7 -> #DIV/0! | F19: =profit!F31*100/profit!F7 -> #DIV/0! | G19: =profit!G31*100/profit!G7 -> #DIV/0! | H19: =profit!H31*100/profit!H7 -> #DIV/0!
A21: Fixed Assets Coverage Ratio | B21: =FACR!B18 -> #DIV/0! | C21: =FACR!C18 -> #DIV/0! | D21: =FACR!D18 -> #DIV/0! | E21: =FACR!E18 -> #DIV/0! | F21: =FACR!F18 -> #DIV/0! | G21: =FACR!G18 -> #DIV/0! | H21: =FACR!H18 -> 0
A23: Return on capital Employed | B23: =ROCE!B20 -> #DIV/0! | C23: =ROCE!C20 -> #DIV/0! | D23: =ROCE!D20 -> #DIV/0! | E23: =ROCE!E20 -> #DIV/0! | F23: =ROCE!F20 -> #DIV/0! | G23: =ROCE!G20 -> #DIV/0! | H23: =ROCE!H20 -> #DIV/0!

Sheet Cost
A1: ='PROJECT AT GLANCE'!D4 -> Malan Food Products Pvt Ltd
A2: ='PROJECT AT GLANCE'!D6 -> Rudreswar, Parbatkash
A7: STATEMENT NO. 1
A9: COST OF THE PROJECT AND MEANS OF FINANCE:
A11: The project cost has been estimated at Rs. | C11: ='PROJECT AT GLANCE'!E19 -> 0
A13: Brief details of the project cost is given below
A15: Cost of the project | B15: : | C15: (Rs.)
A16: Particulars | C16: Total
A17: ='PROJECT AT GLANCE'!B16 -> Stock Purchase | C17: ='PROJECT AT GLANCE'!E16 -> 0
A18: ='PROJECT AT GLANCE'!B17 -> Construction | C18: ='PROJECT AT GLANCE'!E17 -> 0
A19: ='PROJECT AT GLANCE'!B18 -> Machinery & Equipments | C19: ='PROJECT AT GLANCE'!E18 -> 0
A20: Total | C20: =SUM(C17:C19) -> 0
A22: Means of Finance | B22: :
A23: Particulars | C23: Total
A24: Promoters Contribution | C24: ='PROJECT AT GLANCE'!E23 -> 0
A25: Term Loan from Bank / Institution | C25: ='PROJECT AT GLANCE'!E24 -> 0
A26: Cash Credit | C26: ='PROJECT AT GLANCE'!E25 -> 0
A27: Total | C27: =C20 -> 0
A29: Promotors Contribution | C29: =(C24*100/C27)% -> #DIV/0!

Sheet profit
A1: =Cash!A1 -> Malan Food Products Pvt Ltd
A2: STATEMENT NO.2
A3: PROJECTIONS AND PROFITABILITY STATEMENT | H3: In Rs.
A4: PARTICULARS | B4: Operating years
B5: 1 | C5: 2 | D5: 3 | E5: 4 | F5: 5 | G5: 6 | H5: 7
A6: A.
A7: Sales | B7: 0 | C7: =ROUND(B7+(B7*20%),0) -> 0 | D7: =ROUND(C7+(C7*15%),0) -> 0 | E7: =ROUND(D7+(D7*15%),0) -> 0 | F7: =ROUND(E7+(E7*10%),0) -> 0 | G7: =ROUND(F7+(F7*10%),0) -> 0 | H7: =ROUND(G7+(G7*10%),0) -> 0
A8: Other Revenue
B9: =SUM(B7:B8) -> 0 | C9: =SUM(C7:C8) -> 0 | D9: =SUM(D7:D8) -> 0 | E9: =SUM(E7:E8) -> 0 | F9: =SUM(F7:F8) -> 0 | G9: =SUM(G7:G8) -> 0 | H9: =SUM(H7:H8) -> 0
A10: B. EXPENSES:
A11: Purchase | B11: 0 | C11: 0 | D11: 0 | E11: 0 | F11: 0 | G11: 0 | H11: 0
A12: Salary & Wages | B12: 0 | C12: 0 | D12: 0 | E12: 0 | F12: 0 | G12: 0 | H12: 0
A13: Electricity Expense | B13: 0 | C13: =ROUND(B13+(B13*5%),-1) -> 0 | D13: =ROUND(C13+(C13*5%),-1) -> 0 | E13: =ROUND(D13+(D13*5%),-1) -> 0 | F13: =ROUND(E13+(E13*5%),-1) -> 0 | G13: =ROUND(F13+(F13*5%),-1) -> 0 | H13: =ROUND(G13+(G13*5%),-1) -> 0
A14: Misc Expense | B14: 0 | C14: =ROUND(B14+(B14*5%),-1) -> 0 | D14: =ROUND(C14+(C14*5%),-1) -> 0 | E14: =ROUND(D14+(D14*5%),-1) -> 0 | F14: =ROUND(E14+(E14*5%),-1) -> 0 | G14: =ROUND(F14+(F14*5%),-1) -> 0 | H14: =ROUND(G14+(G14*5%),-1) -> 0
A15: Depreciation | B15: =Depr.!B26 -> 0 | C15: =Depr.!C26 -> 0 | D15: =Depr.!D26 -> 0 | E15: =Depr.!E26 -> 0 | F15: =Depr.!F26 -> 0 | G15: =Depr.!G26 -> 0 | H15: =Depr.!H26 -> 0
A16: Cost of Operations | B16: =SUM(B11:B15) -> 0 | C16: =SUM(C11:C15) -> 0 | D16: =SUM(D11:D15) -> 0 | E16: =SUM(E11:E15) -> 0 | F16: =SUM(F11:F15) -> 0 | G16: =SUM(G11:G15) -> 0 | H16: =SUM(H11:H15) -> 0
A18: C. Work Cost [ A - B ] | B18: =B9-B16 -> 0 | C18: =C9-C16 -> 0 | D18: =D9-D16 -> 0 | E18: =E9-E16 -> 0 | F18: =F9-F16 -> 0 | G18: =G9-G16 -> 0 | H18: =H9-H16 -> 0
A20: D. Interest: on loan | B20: 0 | C20: 0 | D20: 0 | E20: 0 | F20: 0 | G20: 0 | H20: 0
A22: Cost Of Production | B22: =B18-B20 -> 0 | C22: =C18-C20 -> 0 | D22: =D18-D20 -> 0 | E22: =E18-E20 -> 0 | F22: =F18-F20 -> 0 | G22: =G18-G20 -> 0 | H22: =H18-H20 -> 0
A24: Add : Opening Stock | B24: 0 | C24: =-B25 -> 0 | D24: =-C25 -> 0 | E24: =-D25 -> 0 | F24: =-E25 -> 0 | G24: =-F25 -> 0 | H24: =-G25 -> 0
A25: Less : Closing Stock | B25: 0 | C25: 0 | D25: 0 | E25: 0 | F25: 0 | G25: 0 | H25: 0
A27: D(1) Cost of Goods Sold | B27: =SUM(B22:B26) -> 0 | C27: =SUM(C22:C26) -> 0 | D27: =SUM(D22:D26) -> 0 | E27: =SUM(E22:E26) -> 0 | F27: =SUM(F22:F26) -> 0 | G27: =SUM(G22:G26) -> 0 | H27: =SUM(H22:H26) -> 0
A29: E. Selling Expense | B29: 0 | C29: 0 | D29: 0 | E29: 0 | F29: 0 | G29: 0 | H29: 0
A31: F. Profit before Tax[ D(1)-E ] | B31: =B27-B29 -> 0 | C31: =C27-C29 -> 0 | D31: =D27-D29 -> 0 | E31: =E27-E29 -> 0 | F31: =F27-F29 -> 0 | G31: =G27-G29 -> 0 | H31: =H27-H29 -> 0
A33: G. Income Tax | B33: 0 | C33: 0 | D33: 0 | E33: 0 | F33: 0 | G33: 0 | H33: 0
A35: H. Profit after Tax ( F-G ) | B35: =B31-B33 -> 0 | C35: =C31-C33 -> 0 | D35: =D31-D33 -> 0 | E35: =E31-E33 -> 0 | F35: =F31-F33 -> 0 | G35: =G31-G33 -> 0 | H35: =H31-H33 -> 0
A37: I. Depreciation added back | B37: =B15 -> 0 | C37: =C15 -> 0 | D37: =D15 -> 0 | E37: =E15 -> 0 | F37: =F15 -> 0 | G37: =G15 -> 0 | H37: =H15 -> 0
A39: J. Cash Accruals ( H + I ) | B39: =B35+B37 -> 0 | C39: =C35+C37 -> 0 | D39: =D35+D37 -> 0 | E39: =E35+E37 -> 0 | F39: =F35+F37 -> 0 | G39: =G35+G37 -> 0 | H39: =H35+H37 -> 0
A41: L. Repayment of Term Loan | B41: 0 | C41: 0 | D41: 0 | E41: 0 | F41: 0 | G41: 0 | H41: 0
A43: M. Net Cash A'ble (J - K)) | B43: =+B39-B41 -> 0 | C43: =+C39-C41 -> 0 | D43: =+D39-D41 -> 0 | E43: =+E39-E41 -> 0 | F43: =+F39-F41 -> 0 | G43: =+G39-G41 -> 0 | H43: =+H39-H41 -> 0
B45: =B7*5% -> 0 | C45: =C7*5% -> 0 | D45: =D7*5% -> 0 | E45: =E7*5% -> 0 | F45: =F7*5% -> 0 | G45: =G7*5% -> 0 | H45: =H7*5% -> 0
B47: =B31-B45 -> 0 | C47: =C31-C45 -> 0 | D47: =D31-D45 -> 0 | E47: =E31-E45 -> 0 | F47: =F31-F45 -> 0 | G47: =G31-G45 -> 0 | H47: =H31-H45 -> 0
B48: =ROUND(B47,-1) -> 0 | C48: =ROUND(C47,-1) -> 0 | D48: =ROUND(D47,-1) -> 0 | E48: =ROUND(E47,-1) -> 0 | F48: =ROUND(F47,-1) -> 0 | G48: =ROUND(G47,-1) -> 0 | H48: =ROUND(H47,-1) -> 0
B54: =70610 -> 70610 | C54: =3000000*12% -> 360000
B55: =C54/12 -> 30000
B56: =B54+B55 -> 100610
B57: =B56/40% -> 251525
B58: =B57*12 -> 3018300
B59: =B58/5% -> 60366000

Sheet B.sheet
A1: =Depr.!A1 -> Malan Food Products Pvt Ltd
A2: STATEMENT No.4
A4: BALANCE SHEET
A6: PARTICULARS | B6: Operating Years
B7: 1 | C7: 2 | D7: 3 | E7: 4 | F7: 5 | G7: 6 | H7: 7
A9: A. LIABILITIES :
A10: Capital Account | B10: ='Capital Account'!B17 -> 0 | C10: ='Capital Account'!C17 -> 0 | D10: ='Capital Account'!D17 -> 0 | E10: ='Capital Account'!E17 -> 0 | F10: ='Capital Account'!F17 -> 0 | G10: ='Capital Account'!G17 -> 0 | H10: ='Capital Account'!H17 -> 0
A11: Term Loan | B11: 0 | C11: 0 | D11: 0 | E11: 0 | F11: 0 | G11: 0 | H11: 0
A12: Cash Credit | B12: 0 | C12: 0 | D12: 0 | E12: 0 | F12: 0 | G12: 0 | H12: 0
A14: TOTAL | B14: =SUM(B10:B12) -> 0 | C14: =SUM(C10:C12) -> 0 | D14: =SUM(D10:D12) -> 0 | E14: =SUM(E10:E12) -> 0 | F14: =SUM(F10:F12) -> 0 | G14: =SUM(G10:G12) -> 0 | H14: =SUM(H10:H12) -> 0
A17: B. ASSETS :
A18: Fixed Assets | B18: =Depr.!B23 -> 0 | C18: =Depr.!C23 -> 0 | D18: =Depr.!D23 -> 0 | E18: =Depr.!E23 -> 0 | F18: =Depr.!F23 -> 0 | G18: =Depr.!G23 -> 0 | H18: =Depr.!H23 -> 0
A19: Investments | B19: 0 | C19: 0 | D19: 0 | E19: 0 | F19: 0 | G19: 0 | H19: 0
A20: Stock in Trade | B20: =profit!B25 -> 0 | C20: =profit!C25 -> 0 | D20: =profit!D25 -> 0 | E20: =profit!E25 -> 0 | F20: =profit!F25 -> 0 | G20: =profit!G25 -> 0 | H20: =profit!H25 -> 0
A21: Cash & Bank | B21: =B23-SUM(B18:B20) -> 0 | C21: =C23-SUM(C18:C20) -> 0 | D21: =D23-SUM(D18:D20) -> 0 | E21: =E23-SUM(E18:E20) -> 0 | F21: =F23-SUM(F18:F20) -> 0 | G21: =G23-SUM(G18:G20) -> 0 | H21: =H23-SUM(H18:H20) -> 0
A23: TOTAL | B23: =B14 -> 0 | C23: =C14 -> 0 | D23: =D14 -> 0 | E23: =E14 -> 0 | F23: =F14 -> 0 | G23: =G14 -> 0 | H23: =H14 -> 0

Sheet Cash
A1: =B.sheet!A1 -> Malan Food Products Pvt Ltd
A2: STATEMENT No.3
A4: CASH - FLOW STATEMENT :
A6: PARTICULARS | B6: Operating Years
B7: 1 | C7: 2 | D7: 3 | E7: 4 | F7: 5 | G7: 6 | H7: 7
A8: A. Source of Funds :
A9: Profit after Tax | B9: =profit!B35 -> 0 | C9: =profit!C35 -> 0 | D9: =profit!D35 -> 0 | E9: =profit!E35 -> 0 | F9: =profit!F35 -> 0 | G9: =profit!G35 -> 0 | H9: =profit!H35 -> 0
A10: Depreciation | B10: =profit!B15 -> 0 | C10: =+profit!C15 -> 0 | D10: =+profit!D15 -> 0 | E10: =+profit!E15 -> 0 | F10: =+profit!F15 -> 0 | G10: =+profit!G15 -> 0 | H10: =+profit!H15 -> 0
A11: Loan from Bank | B11: =Cost!C25+Cost!C26 -> 0 | C11: 0 | D11: 0 | E11: 0 | F11: 0 | G11: 0 | H11: 0
A12: Provision For Tax | B12: =profit!B33 -> 0 | C12: =profit!C33 -> 0 | D12: =profit!D33 -> 0 | E12: =profit!E33 -> 0 | F12: =profit!F33 -> 0 | G12: =profit!G33 -> 0 | H12: =profit!H33 -> 0
A14: TOTAL OF ' A ' | B14: =SUM(B9:B13) -> 0 | C14: =SUM(C9:C13) -> 0 | D14: =SUM(D9:D13) -> 0 | E14: =SUM(E9:E13) -> 0 | F14: =SUM(F9:F13) -> 0 | G14: =SUM(G9:G13) -> 0 | H14: =SUM(H9:H13) -> 0
A16: B. Application of Funds :
A17: Fixed Assets Purchased | B17: =Depr.!B14+Depr.!B20 -> 0 | C17: =Depr.!C20-Depr.!B20 -> 0 | D17: =Depr.!D20-Depr.!C20 -> 0 | E17: =Depr.!E20-Depr.!D20 -> 0 | F17: =Depr.!F20-Depr.!E20 -> 0 | G17: =Depr.!G20-Depr.!F20 -> 0 | H17: =Depr.!H20-Depr.!G20 -> 0
A18: Investments | B18: =B.sheet!B19 -> 0 | C18: =B.sheet!C19-B.sheet!B19 -> 0 | D18: =B.sheet!D19-B.sheet!C19 -> 0 | E18: =B.sheet!E19-B.sheet!D19 -> 0 | F18: =B.sheet!F19-B.sheet!E19 -> 0 | G18: =B.sheet!G19-B.sheet!F19 -> 0 | H18: =B.sheet!H19-B.sheet!G19 -> 0
A19: Repayment of loan | B19: =profit!B41 -> 0 | C19: =profit!C41 -> 0 | D19: =profit!D41 -> 0 | E19: =profit!E41 -> 0 | F19: =profit!F41 -> 0 | G19: =profit!G41 -> 0 | H19: =profit!H41 -> 0
A20: Increase in Current Assets | B20: =B.sheet!B20 -> 0 | C20: =B.sheet!C20-B.sheet!B20 -> 0 | D20: =B.sheet!D20-B.sheet!C20 -> 0 | E20: =B.sheet!E20-B.sheet!D20 -> 0 | F20: =B.sheet!F20-B.sheet!E20 -> 0 | G20: =B.sheet!G20-B.sheet!F20 -> 0 | H20: =B.sheet!H20-B.sheet!G20 -> 0
A21: Personal Withdraw | B21: ='Capital Account'!B15 -> 0 | C21: ='Capital Account'!C15 -> 0 | D21: ='Capital Account'!D15 -> 0 | E21: ='Capital Account'!E15 -> 0 | F21: ='Capital Account'!F15 -> 0 | G21: ='Capital Account'!G15 -> 0 | H21: ='Capital Account'!H15 -> 0
A23: TOTAL OF ' B ' | B23: =SUM(B17:B21) -> 0 | C23: =SUM(C17:C21) -> 0 | D23: =SUM(D17:D21) -> 0 | E23: =SUM(E17:E21) -> 0 | F23: =SUM(F17:F21) -> 0 | G23: =SUM(G17:G21) -> 0 | H23: =SUM(H17:H21) -> 0
A26: C. Opening Balance | B26: =Cost!C24 -> 0 | C26: =B30 -> 0 | D26: =C30 -> 0 | E26: =D30 -> 0 | F26: =E30 -> 0 | G26: =F30 -> 0 | H26: =G30 -> 0
A28: D. Net surplus ( A - B ) | B28: =B14-B23 -> 0 | C28: =C14-C23 -> 0 | D28: =D14-D23 -> 0 | E28: =E14-E23 -> 0 | F28: =F14-F23 -> 0 | G28: =G14-G23 -> 0 | H28: =H14-H23 -> 0
A30: E. Closing Balance | B30: =B26+B28 -> 0 | C30: =C26+C28 -> 0 | D30: =D26+D28 -> 0 | E30: =E26+E28 -> 0 | F30: =F26+F28 -> 0 | G30: =G26+G28 -> 0 | H30: =H26+H28 -> 0
XFD33: =B.sheet!XFD21 -> 0

Sheet Depr.
A1: =Cost!A1 -> Malan Food Products Pvt Ltd
A2: =Cost!A2 -> Rudreswar, Parbatkash
A6: ANNEXURE NO.1
A8: DEPRECIATION SCHEDULE:
A9: PARTICULARS | B9: WDV at the year end
B10: 1 | C10: 2 | D10: 3 | E10: 4 | F10: 5 | G10: 6 | H10: 7
A12: 1. Machinery & Equipments
A13: Opening Balance : | B13: 0 | C13: =B18 -> 0 | D13: =C18 -> 0 | E13: =D18 -> 0 | F13: =E18 -> 0 | G13: =F18 -> 0 | H13: =G18 -> 0
A14: Addition | B14: ='PROJECT AT GLANCE'!E18 -> 0 | C14: 0 | D14: 0 | E14: 0 | F14: 0 | G14: 0 | H14: 0
A15: Total | B15: =SUM(B12:B14) -> 0 | C15: =SUM(C12:C14) -> 0 | D15: =SUM(D12:D14) -> 0 | E15: =SUM(E12:E14) -> 0 | F15: =SUM(F12:F14) -> 0 | G15: =SUM(G12:G14) -> 0 | H15: =SUM(H12:H14) -> 0
A17: Less : Depriciation | B17: =ROUND(B15*15%,0) -> 0 | C17: =ROUND(C15*15%,0) -> 0 | D17: =ROUND(D15*15%,0) -> 0 | E17: =ROUND(E15*15%,0) -> 0 | F17: =ROUND(F15*15%,0) -> 0 | G17: =ROUND(G15*15%,0) -> 0 | H17: =ROUND(H15*15%,0) -> 0
A18: Closing Balance : | B18: =B15-B17 -> 0 | C18: =C15-C17 -> 0 | D18: =D15-D17 -> 0 | E18: =E15-E17 -> 0 | F18: =F15-F17 -> 0 | G18: =G15-G17 -> 0 | H18: =H15-H17 -> 0
A20: Construction | B20: ='PROJECT AT GLANCE'!E17 -> 0 | C20: 0 | D20: 0 | E20: 0 | F20: 0 | G20: 0 | H20: 0
A22: Total Assets
A23: [1+2+3+4] | B23: =B18+B20 -> 0 | C23: =C18+C20 -> 0 | D23: =D18+D20 -> 0 | E23: =E18+E20 -> 0 | F23: =F18+F20 -> 0 | G23: =G18+G20 -> 0 | H23: =H18+H20 -> 0
A25: Total Depreciation
A26: [1+2+3+4] | B26: =B17 -> 0 | C26: =C17 -> 0 | D26: =D17 -> 0 | E26: =E17 -> 0 | F26: =F17 -> 0 | G26: =G17 -> 0 | H26: =H17 -> 0

Sheet Capital Account
A1: =Depr.!A1 -> Malan Food Products Pvt Ltd
A2: STATEMENT No.2
A4: CAPITAL ACCOUNT
A6: PARTICULARS | B6: Operating Years
B7: 1 | C7: 2 | D7: 3 | E7: 4 | F7: 5 | G7: 6 | H7: 7
A9: Opening Balance :
A10: Capital Account | B10: =Cost!C24 -> 0 | C10: =B17 -> 0 | D10: =C17 -> 0 | E10: =D17 -> 0 | F10: =E17 -> 0 | G10: =F17 -> 0 | H10: =G17 -> 0
A11: Net Profit | B11: =profit!B31 -> 0 | C11: =profit!C31 -> 0 | D11: =profit!D31 -> 0 | E11: =profit!E31 -> 0 | F11: =profit!F31 -> 0 | G11: =profit!G31 -> 0 | H11: =profit!H31 -> 0
A13: TOTAL | B13: =SUM(B10:B12) -> 0 | C13: =SUM(C10:C12) -> 0 | D13: =SUM(D10:D12) -> 0 | E13: =SUM(E10:E12) -> 0 | F13: =SUM(F10:F12) -> 0 | G13: =SUM(G10:G12) -> 0 | H13: =SUM(H10:H12) -> 0
A15: Less : Personal Withdrawls | B15: 0 | C15: 0 | D15: 0 | E15: 0 | F15: 0 | G15: 0 | H15: 0
A17: Closing Balance | B17: =B13-B15 -> 0 | C17: =C13-C15 -> 0 | D17: =D13-D15 -> 0 | E17: =E13-E15 -> 0 | F17: =F13-F15 -> 0 | G17: =G13-G15 -> 0 | H17: =H13-H15 -> 0

Sheet BEP
A1: =profit!A1 -> Malan Food Products Pvt Ltd
A2: ANNEXURE NO.2
A4: BREAK-EVEN ANALYSIS
A5: Particulars | B5: Years
B6: 1 | C6: 2 | D6: 3 | E6: 4 | F6: 5 | G6: 6 | H6: 7
A7: A. Receipts | B7: =profit!B7 -> 0 | C7: =profit!C7 -> 0 | D7: =profit!D7 -> 0 | E7: =profit!E7 -> 0 | F7: =profit!F7 -> 0 | G7: =profit!G7 -> 0 | H7: =profit!H7 -> 0
A9: B. Variable cost: | B9: =profit!B16 -> 0 | C9: =profit!C16 -> 0 | D9: =profit!D16 -> 0 | E9: =profit!E16 -> 0 | F9: =profit!F16 -> 0 | G9: =profit!G16 -> 0 | H9: =profit!H16 -> 0
A12: C. Fixed costs:
A13: Depreciation | B13: =profit!B15 -> 0 | C13: =profit!C15 -> 0 | D13: =profit!D15 -> 0 | E13: =profit!E15 -> 0 | F13: =profit!F15 -> 0 | G13: =profit!G15 -> 0 | H13: =profit!H15 -> 0
A14: Interest on Loan | B14: =profit!B20 -> 0 | C14: =profit!C20 -> 0 | D14: =profit!D20 -> 0 | E14: =profit!E20 -> 0 | F14: =profit!F20 -> 0 | G14: =profit!G20 -> 0 | H14: =profit!H20 -> 0
A15: Administration Expenses | B15: 0 | C15: 0 | D15: 0 | E15: 0 | F15: 0 | G15: 0 | H15: 0
B16: =SUM(B13:B15) -> 0 | C16: =SUM(C13:C15) -> 0 | D16: =SUM(D13:D15) -> 0 | E16: =SUM(E13:E15) -> 0 | F16: =SUM(F13:F15) -> 0 | G16: =SUM(G13:G15) -> 0 | H16: =SUM(H13:H15) -> 0
A18: D. Contribution [ A- B ] | B18: =B7-B9 -> 0 | C18: =C7 - C9 -> 0 | D18: =D7 - D9 -> 0 | E18: =E7 - E9 -> 0 | F18: =F7 - F9 -> 0 | G18: =G7 - G9 -> 0 | H18: =H7 - H9 -> 0
A20: F. P.V.Ratio [ E/B x 100 ] | B20: =B18/B7*100 -> #DIV/0! | C20: =C18/C7*100 -> #DIV/0! | D20: =D18/D7*100 -> #DIV/0! | E20: =E18/E7*100 -> #DIV/0! | F20: =F18/F7*100 -> #DIV/0! | G20: =G18/G7*100 -> #DIV/0! | H20: =H18/H7*100 -> #DIV/0!
A22: G. Break - even [ Value ]
A23: [ D / F x 100 ] | B23: =B16/B20*100 -> #DIV/0! | C23: =C16/C20*100 -> #DIV/0! | D23: =D16/D20*100 -> #DIV/0! | E23: =E16/E20*100 -> #DIV/0! | F23: =F16/F20*100 -> #DIV/0! | G23: =G16/G20*100 -> #DIV/0! | H23: =H16/H20*100 -> #DIV/0!
A25: H. Cash Break Even | B25: =(B16-B13)/B20*100 -> #DIV/0! | C25: =(C16-C13)/C20*100 -> #DIV/0! | D25: =(D16-D13)/D20*100 -> #DIV/0! | E25: =(E16-E13)/E20*100 -> #DIV/0! | F25: =(F16-F13)/F20*100 -> #DIV/0! | G25: =(G16-G13)/G20*100 -> #DIV/0! | H25: =(H16-H13)/H20*100 -> #DIV/0!
A26: [ Without Depreciation]

Sheet ROCE
A1: ='Capital Account'!A1 -> Malan Food Products Pvt Ltd
A2: ANNEXURE NO.4
A4: RETURN ON CAPITAL EMPLOYED :
A5: Particulars | B5: Operating Years
B6: 1 | C6: 2 | D6: 3 | E6: 4 | F6: 5 | G6: 6 | H6: 7
A7: A. EBIT :
A8: Profit after tax | B8: =profit!B35 -> 0 | C8: =profit!C35 -> 0 | D8: =profit!D35 -> 0 | E8: =profit!E35 -> 0 | F8: =profit!F35 -> 0 | G8: =profit!G35 -> 0 | H8: =profit!H35 -> 0
A9: Tax | B9: =profit!B33 -> 0 | C9: =profit!C33 -> 0 | D9: =profit!D33 -> 0 | E9: =profit!E33 -> 0 | F9: =profit!F33 -> 0 | G9: =profit!G33 -> 0 | H9: =profit!H33 -> 0
A10: Interest on loan | B10: =profit!B20 -> 0 | C10: =profit!C20 -> 0 | D10: =profit!D20 -> 0 | E10: =profit!E20 -> 0 | F10: =profit!F20 -> 0 | G10: =profit!G20 -> 0 | H10: =profit!H20 -> 0
A11: TOTAL OF ' A ' | B11: =SUM(B8:B10) -> 0 | C11: =SUM(C8:C10) -> 0 | D11: =SUM(D8:D10) -> 0 | E11: =SUM(E8:E10) -> 0 | F11: =SUM(F8:F10) -> 0 | G11: =SUM(G8:G10) -> 0 | H11: =SUM(H8:H10) -> 0
A13: B. CAPITAL EMPLOYED :
A14: Total Assets | B14: =B.sheet!B23 -> 0 | C14: =B.sheet!C23 -> 0 | D14: =B.sheet!D23 -> 0 | E14: =B.sheet!E23 -> 0 | F14: =B.sheet!F23 -> 0 | G14: =B.sheet!G23 -> 0 | H14: =B.sheet!H23 -> 0
A15: Less : Current Liabilities | B15: =-B.sheet!B12 -> 0 | C15: =-B.sheet!C12 -> 0 | D15: =-B.sheet!D12 -> 0 | E15: =-B.sheet!E12 -> 0 | F15: =-B.sheet!F12 -> 0 | G15: =-B.sheet!G12 -> 0 | H15: =-B.sheet!H12 -> 0
A17: TOTAL OF ' B ' | B17: =SUM(B14:B16) -> 0 | C17: =SUM(C14:C16) -> 0 | D17: =SUM(D14:D16) -> 0 | E17: =SUM(E14:E16) -> 0 | F17: =SUM(F14:F16) -> 0 | G17: =SUM(G14:G16) -> 0 | H17: =SUM(H14:H16) -> 0
A19: C Return on Capital Employed
A20: ROCE [ A / B ] | B20: =B11/B17 -> #DIV/0! | C20: =C11/C17 -> #DIV/0! | D20: =D11/D17 -> #DIV/0! | E20: =E11/E17 -> #DIV/0! | F20: =F11/F17 -> #DIV/0! | G20: =G11/G17 -> #DIV/0! | H20: =H11/H17 -> #DIV/0!
A22: D Average DSCR | B22: =AVERAGE(B20:H20) -> #DIV/0!

Sheet DSCR
A1: ='Capital Account'!A1 -> Malan Food Products Pvt Ltd
A2: ANNEXURE NO.4
A4: DEBT SERVICE COVERAGE RATIO :
A5: Particulars | B5: Operating Years
B6: 1 | C6: 2 | D6: 3 | E6: 4 | F6: 5 | G6: 6 | H6: 7
A7: A. SOURCES :
A8: Profit after tax | B8: =+profit!B35 -> 0 | C8: =+profit!C35 -> 0 | D8: =+profit!D35 -> 0 | E8: =+profit!E35 -> 0 | F8: =+profit!F35 -> 0 | G8: =+profit!G35 -> 0 | H8: =+profit!H35 -> 0
A9: Depreciation | B9: =+profit!B37 -> 0 | C9: =+profit!C37 -> 0 | D9: =+profit!D37 -> 0 | E9: =+profit!E37 -> 0 | F9: =+profit!F37 -> 0 | G9: =+profit!G37 -> 0 | H9: =+profit!H37 -> 0
A10: Interest on loan | B10: =profit!B20 -> 0 | C10: =profit!C20 -> 0 | D10: =profit!D20 -> 0 | E10: =profit!E20 -> 0 | F10: =profit!F20 -> 0 | G10: =profit!G20 -> 0 | H10: =profit!H20 -> 0
A11: TOTAL OF ' A ' | B11: =SUM(B8:B10) -> 0 | C11: =SUM(C8:C10) -> 0 | D11: =SUM(D8:D10) -> 0 | E11: =SUM(E8:E10) -> 0 | F11: =SUM(F8:F10) -> 0 | G11: =SUM(G8:G10) -> 0 | H11: =SUM(H8:H10) -> 0
A13: B DEBT :
A14: Term loan installment | B14: =+Cash!B19 -> 0 | C14: =+Cash!C19 -> 0 | D14: =+Cash!D19 -> 0 | E14: =+Cash!E19 -> 0 | F14: =+Cash!F19 -> 0 | G14: =+Cash!G19 -> 0 | H14: =+Cash!H19 -> 0
A15: Interest on Term Loan | B15: =+profit!B20 -> 0 | C15: =+profit!C20 -> 0 | D15: =+profit!D20 -> 0 | E15: =+profit!E20 -> 0 | F15: =+profit!F20 -> 0 | G15: =+profit!G20 -> 0 | H15: =+profit!H20 -> 0
A17: TOTAL OF ' B ' | B17: =SUM(B14:B16) -> 0 | C17: =SUM(C14:C16) -> 0 | D17: =SUM(D14:D16) -> 0 | E17: =SUM(E14:E16) -> 0 | F17: =SUM(F14:F16) -> 0 | G17: =SUM(G14:G16) -> 0 | H17: =SUM(H14:H16) -> 0
A19: C Debt Service Coverage Ratio
A20: DSCR [ A / B ] | B20: =B11/B17 -> #DIV/0! | C20: =C11/C17 -> #DIV/0! | D20: =D11/D17 -> #DIV/0! | E20: =E11/E17 -> #DIV/0! | F20: =F11/F17 -> #DIV/0! | G20: =G11/G17 -> #DIV/0! | H20: =H11/H17 -> #DIV/0!
A22: D Average DSCR | B22: =AVERAGE(B20:H20) -> #DIV/0!

Sheet FACR
A1: =DSCR!A1 -> Malan Food Products Pvt Ltd
A2: ANNEXURE NO.5
A4: FIXED ASSETS COVERAGE RATIO :
A5: Particulars | B5: Operating Years
B6: 1 | C6: 2 | D6: 3 | E6: 4 | F6: 5 | G6: 6 | H6: 7
A7: A. Net Fixed Assets
A8: Fixed Assets | B8: =B.sheet!B18 -> 0 | C8: =B.sheet!C18 -> 0 | D8: =B.sheet!D18 -> 0 | E8: =B.sheet!E18 -> 0 | F8: =B.sheet!F18 -> 0 | G8: =B.sheet!G18 -> 0 | H8: =B.sheet!H18 -> 0
A10: TOTAL OF ' A ' | B10: =SUM(B7:B8) -> 0 | C10: =SUM(C7:C8) -> 0 | D10: =SUM(D7:D8) -> 0 | E10: =SUM(E7:E8) -> 0 | F10: =SUM(F7:F8) -> 0 | G10: =SUM(G7:G8) -> 0 | H10: =SUM(H7:H8) -> 0
A12: B. Long Term/Medium Term Loans
A13: Term loan installment | B13: =B.sheet!B11 -> 0 | C13: =B.sheet!C11 -> 0 | D13: =B.sheet!D11 -> 0 | E13: =B.sheet!E11 -> 0 | F13: =B.sheet!F11 -> 0 | G13: =B.sheet!G11 -> 0 | H13: =B.sheet!H11 -> 0
A15: TOTAL OF ' B ' | B15: =SUM(B13:B14) -> 0 | C15: =SUM(C13:C14) -> 0 | D15: =SUM(D13:D14) -> 0 | E15: =SUM(E13:E14) -> 0 | F15: =SUM(F13:F14) -> 0 | G15: =SUM(G13:G14) -> 0 | H15: =SUM(H13:H14) -> 0
A17: C FACR
A18: [ A / B ] | B18: =B10/B15 -> #DIV/0! | C18: =C10/C15 -> #DIV/0! | D18: =D10/D15 -> #DIV/0! | E18: =E10/E15 -> #DIV/0! | F18: =F10/F15 -> #DIV/0! | G18: =G10/G15 -> #DIV/0! | H18: 0
A20: D Average CR | B20: =AVERAGE(B18:H18) -> #DIV/0!

Sheet Current Ratio
A1: =DSCR!A1 -> Malan Food Products Pvt Ltd
A2: ANNEXURE NO.5
A4: CURRENT RATIO :
A5: Particulars | B5: Operating Years
B6: 1 | C6: 2 | D6: 3 | E6: 4 | F6: 5 | G6: 6 | H6: 7
A7: A. Current Assets
A8: Stock in Trade | B8: =B.sheet!B20 -> 0 | C8: =B.sheet!C20 -> 0 | D8: =B.sheet!D20 -> 0 | E8: =B.sheet!E20 -> 0 | F8: =B.sheet!F20 -> 0 | G8: =B.sheet!G20 -> 0 | H8: =B.sheet!H20 -> 0
A9: Cash & Bank | B9: =B.sheet!B21 -> 0 | C9: =B.sheet!C21 -> 0 | D9: =B.sheet!D21 -> 0 | E9: =B.sheet!E21 -> 0 | F9: =B.sheet!F21 -> 0 | G9: =B.sheet!G21 -> 0 | H9: =B.sheet!H21 -> 0
A11: TOTAL OF ' A ' | B11: =SUM(B7:B9) -> 0 | C11: =SUM(C7:C9) -> 0 | D11: =SUM(D7:D9) -> 0 | E11: =SUM(E7:E9) -> 0 | F11: =SUM(F7:F9) -> 0 | G11: =SUM(G7:G9) -> 0 | H11: =SUM(H7:H9) -> 0
A13: B. Current Liabilities
A14: Term loan installment | B14: =+Cash!B19 -> 0 | C14: =+Cash!C19 -> 0 | D14: =+Cash!D19 -> 0 | E14: =+Cash!E19 -> 0 | F14: =+Cash!F19 -> 0 | G14: =+Cash!G19 -> 0 | H14: =+Cash!H19 -> 0
A15: Cash Credit | B15: =B.sheet!B12 -> 0 | C15: =B.sheet!C12 -> 0 | D15: =B.sheet!D12 -> 0 | E15: =B.sheet!E12 -> 0 | F15: =B.sheet!F12 -> 0 | G15: =B.sheet!G12 -> 0 | H15: =B.sheet!H12 -> 0
A17: TOTAL OF ' B ' | B17: =SUM(B14:B16) -> 0 | C17: =SUM(C14:C16) -> 0 | D17: =SUM(D14:D16) -> 0 | E17: =SUM(E14:E16) -> 0 | F17: =SUM(F14:F16) -> 0 | G17: =SUM(G14:G16) -> 0 | H17: =SUM(H14:H16) -> 0
A19: C Current Ratio
A20: [ A / B ] | B20: =B11/B17 -> #DIV/0! | C20: =C11/C17 -> #DIV/0! | D20: =D11/D17 -> #DIV/0! | E20: =E11/E17 -> #DIV/0! | F20: =F11/F17 -> #DIV/0! | G20: =G11/G17 -> #DIV/0! | H20: =H11/H17 -> #DIV/0!
A22: D Average CR | B22: =AVERAGE(B20:H20) -> #DIV/0!

Sheet Quick ratio
A1: =DSCR!A1 -> Malan Food Products Pvt Ltd
A2: ANNEXURE NO.5
A4: QUICK RATIO :
A5: Particulars | B5: Operating Years
B6: 1 | C6: 2 | D6: 3 | E6: 4 | F6: 5 | G6: 6 | H6: 7
A7: A. Lequid Assets
A8: Cash & Bank | B8: =B.sheet!B21 -> 0 | C8: =B.sheet!C21 -> 0 | D8: =B.sheet!D21 -> 0 | E8: =B.sheet!E21 -> 0 | F8: =B.sheet!F21 -> 0 | G8: =B.sheet!G21 -> 0 | H8: =B.sheet!H21 -> 0
A10: TOTAL OF ' A ' | B10: =SUM(B7:B8) -> 0 | C10: =SUM(C7:C8) -> 0 | D10: =SUM(D7:D8) -> 0 | E10: =SUM(E7:E8) -> 0 | F10: =SUM(F7:F8) -> 0 | G10: =SUM(G7:G8) -> 0 | H10: =SUM(H7:H8) -> 0
A12: B. Current Liabilities
A13: Term loan installment | B13: =+Cash!B19 -> 0 | C13: =+Cash!C19 -> 0 | D13: =+Cash!D19 -> 0 | E13: =+Cash!E19 -> 0 | F13: =+Cash!F19 -> 0 | G13: =+Cash!G19 -> 0 | H13: =+Cash!H19 -> 0
A14: Cash Credit | B14: =B.sheet!B12 -> 0 | C14: =B.sheet!C12 -> 0 | D14: =B.sheet!D12 -> 0 | E14: =B.sheet!E12 -> 0 | F14: =B.sheet!F12 -> 0 | G14: =B.sheet!G12 -> 0 | H14: =B.sheet!H12 -> 0
A16: TOTAL OF ' B ' | B16: =SUM(B13:B15) -> 0 | C16: =SUM(C13:C15) -> 0 | D16: =SUM(D13:D15) -> 0 | E16: =SUM(E13:E15) -> 0 | F16: =SUM(F13:F15) -> 0 | G16: =SUM(G13:G15) -> 0 | H16: =SUM(H13:H15) -> 0
A18: C Quick Ratio
A19: [ A / B ] | B19: =B10/B16 -> #DIV/0! | C19: =C10/C16 -> #DIV/0! | D19: =D10/D16 -> #DIV/0! | E19: =E10/E16 -> #DIV/0! | F19: =F10/F16 -> #DIV/0! | G19: =G10/G16 -> #DIV/0! | H19: =H10/H16 -> #DIV/0!
A21: D Average CR | B21: =AVERAGE(B19:H19) -> #DIV/0!

Sheet TOL TNW
A1: =DSCR!A1 -> Malan Food Products Pvt Ltd
A2: ANNEXURE NO.6
A4: TOL/TNW
A5: Particulars | B5: Operating Years
B6: 1 | C6: 2 | D6: 3 | E6: 4 | F6: 5 | G6: 6 | H6: 7
A7: A. Total Outside Liabilities
A8: Term Loan | B8: =B.sheet!B11 -> 0 | C8: =B.sheet!C11 -> 0 | D8: =B.sheet!D11 -> 0 | E8: =B.sheet!E11 -> 0 | F8: =B.sheet!F11 -> 0 | G8: =B.sheet!G11 -> 0 | H8: =B.sheet!H11 -> 0
A9: Cash Credit | B9: =B.sheet!B12 -> 0 | C9: =B.sheet!C12 -> 0 | D9: =B.sheet!D12 -> 0 | E9: =B.sheet!E12 -> 0 | F9: =B.sheet!F12 -> 0 | G9: =B.sheet!G12 -> 0 | H9: =B.sheet!H12 -> 0
A11: TOTAL OF ' A ' | B11: =SUM(B8:B10) -> 0 | C11: =SUM(C8:C10) -> 0 | D11: =SUM(D8:D10) -> 0 | E11: =SUM(E8:E10) -> 0 | F11: =SUM(F8:F10) -> 0 | G11: =SUM(G8:G10) -> 0 | H11: =SUM(H8:H10) -> 0
A13: B Total Net Worth
A14: Proprietors Capital | B14: =B.sheet!B10 -> 0 | C14: =B.sheet!C10 -> 0 | D14: =B.sheet!D10 -> 0 | E14: =B.sheet!E10 -> 0 | F14: =B.sheet!F10 -> 0 | G14: =B.sheet!G10 -> 0 | H14: =B.sheet!H10 -> 0
A16: TOTAL OF ' B ' | B16: =SUM(B14:B15) -> 0 | C16: =SUM(C14:C15) -> 0 | D16: =SUM(D14:D15) -> 0 | E16: =SUM(E14:E15) -> 0 | F16: =SUM(F14:F15) -> 0 | G16: =SUM(G14:G15) -> 0 | H16: =SUM(H14:H15) -> 0
A18: C TOL/TNW
A19: [ A / B ] | B19: =B11/B16 -> #DIV/0! | C19: =C11/C16 -> #DIV/0! | D19: =D11/D16 -> #DIV/0! | E19: =E11/E16 -> #DIV/0! | F19: =F11/F16 -> #DIV/0! | G19: =G11/G16 -> #DIV/0! | H19: =H11/H16 -> #DIV/0!
A21: D Average TOL/TNW | B21: =AVERAGE(B19:H19) -> #DIV/0!

Sheet DEBT EQUITY
A1: =DSCR!A1 -> Malan Food Products Pvt Ltd
A2: ANNEXURE NO.7
A4: DEBT EQUITY RATIO
A5: Particulars | B5: Operating Years
B6: 1 | C6: 2 | D6: 3 | E6: 4 | F6: 5 | G6: 6 | H6: 7
A7: A. Total Long Term Debts
A8: Term Loan | B8: =B.sheet!B11 -> 0 | C8: =B.sheet!C11 -> 0 | D8: =B.sheet!D11 -> 0 | E8: =B.sheet!E11 -> 0 | F8: =B.sheet!F11 -> 0 | G8: =B.sheet!G11 -> 0 | H8: =B.sheet!H11 -> 0
A9: Cash Credit | B9: =B.sheet!B12 -> 0 | C9: =B.sheet!C12 -> 0 | D9: =B.sheet!D12 -> 0 | E9: =B.sheet!E12 -> 0 | F9: =B.sheet!F12 -> 0 | G9: =B.sheet!G12 -> 0 | H9: =B.sheet!H12 -> 0
A11: TOTAL OF ' A ' | B11: =SUM(B8:B10) -> 0 | C11: =SUM(C8:C10) -> 0 | D11: =SUM(D8:D10) -> 0 | E11: =SUM(E8:E10) -> 0 | F11: =SUM(F8:F10) -> 0 | G11: =SUM(G8:G10) -> 0 | H11: =SUM(H8:H10) -> 0
A13: B Total Equity
A14: Proprietors Capital | B14: =B.sheet!B10 -> 0 | C14: =B.sheet!C10 -> 0 | D14: =B.sheet!D10 -> 0 | E14: =B.sheet!E10 -> 0 | F14: =B.sheet!F10 -> 0 | G14: =B.sheet!G10 -> 0 | H14: =B.sheet!H10 -> 0
A16: TOTAL OF ' B ' | B16: =SUM(B14:B15) -> 0 | C16: =SUM(C14:C15) -> 0 | D16: =SUM(D14:D15) -> 0 | E16: =SUM(E14:E15) -> 0 | F16: =SUM(F14:F15) -> 0 | G16: =SUM(G14:G15) -> 0 | H16: =SUM(H14:H15) -> 0
A18: C D/E Ratio
A19: [ A / B ] | B19: =B11/B16 -> #DIV/0! | C19: =C11/C16 -> #DIV/0! | D19: =D11/D16 -> #DIV/0! | E19: =E11/E16 -> #DIV/0! | F19: =F11/F16 -> #DIV/0! | G19: =G11/G16 -> #DIV/0! | H19: =H11/H16 -> #DIV/0!
A21: D Average Debt Equity | B21: =AVERAGE(B19:H19) -> #DIV/0!

Sheet Salary
A4: Salary Statement
B6: MAN POWER REQUIRMENTS
E7: YEAR-1 | F7: YEAR-2 | G7: YEAR-3 | H7: YEAR-4 | I7: YEAR-5 | J7: YEAR-6 | K7: YEAR-7
A8: Sl. | B8: Designation | C8: Number | D8: Rate | E8: Salary | F8: Salary | G8: Salary | H8: Salary | I8: Salary | J8: Salary | K8: Salary
A9: No. | F9: (Rs./Year) | G9: (Rs./Year) | H9: (Rs./Year) | I9: (Rs./Year) | J9: (Rs./Year) | K9: (Rs./Year)
A10: A. | B10: ADMINISTRATION :
B11: Manager | C11: 1 | D11: 15000 | E11: =D11*12 -> 180000 | F11: =16000*12 -> 192000 | G11: =17000*12 -> 204000 | H11: =18000*12 -> 216000 | I11: =19000*12 -> 228000 | J11: =20000*12 -> 240000 | K11: =21000*12 -> 252000
A12: B. | B12: PRODUCTION :
B13: Supervisor | C13: 1 | D13: 12000 | E13: =D13*12 -> 144000 | F13: =13000*12 -> 156000 | G13: =14000*12 -> 168000 | H13: =15000*12 -> 180000 | I13: =16000*12 -> 192000 | J13: =17000*12 -> 204000 | K13: =18000*12 -> 216000
B14: Staff | C14: 5 | D14: =5000*5 -> 25000 | E14: =D14*12 -> 300000 | F14: =30000*12 -> 360000 | G14: =35000*12 -> 420000 | H14: =40000*12 -> 480000 | I14: =45000*12 -> 540000 | J14: =50000*12 -> 600000 | K14: =55000*12 -> 660000
B15: Guard | C15: 1 | D15: 10000 | E15: =D15*12 -> 120000 | F15: =11000*12 -> 132000 | G15: =12000*12 -> 144000 | H15: =13000*12 -> 156000 | I15: =14000*12 -> 168000 | J15: =15000*12 -> 180000 | K15: =16000*12 -> 192000
B17: Total | C17: =SUM(C11:C15) -> 8 | E17: =SUM(E11:E16) -> 744000 | F17: =SUM(F11:F16) -> 840000 | G17: =SUM(G11:G16) -> 936000 | H17: =SUM(H11:H16) -> 1032000 | I17: =SUM(I11:I16) -> 1128000 | J17: =SUM(J11:J16) -> 1224000 | K17: =SUM(K11:K16) -> 1320000

Sheet Current Assets Chart
C6: Row Labels | D6: Sum of Current Asste | E6: Sum of Current Liability
C7: 1 | D7: 5305079 | E7: 3388223
C8: 2 | D8: 5930828 | E8: 3437460
C9: 3 | D9: 7315707 | E9: 3492939
C10: 4 | D10: 8888467 | E10: 3555458
C11: 5 | D11: 10849061 | E11: 3625904
C12: 6 | D12: 13279559 | E12: 3705283
C13: 7 | D13: 14945229 | E13: 3794731
C14: Grand Total | D14: 66513930 | E14: 24999998
D23: Year | E23: Current Asste | F23: Current Liability
D24: 1 | E24: 0 | F24: 0
D25: 2 | E25: 0 | F25: 0
D26: 3 | E26: 0 | F26: 0
D27: 4 | E27: 0 | F27: 0
D28: 5 | E28: 0 | F28: 0
D29: 6 | E29: 0 | F29: 0
D30: 7 | E30: 0 | F30: 0

Sheet Profit Chart
E23: YEAR | F23: PROFIT
E24: 1 | F24: 0
E25: 2 | F25: 0
E26: 3 | F26: 0
E27: 4 | F27: 0
E28: 5 | F28: 0
E29: 6 | F29: 0
E30: 7 | F30: 0

Sheet Sales Chart
E23: YEAR | F23: SALES
E24: 1 | F24: 0
E25: 2 | F25: 0
E26: 3 | F26: 0
E27: 4 | F27: 0
E28: 5 | F28: 0
E29: 6 | F29: 0
E30: 7 | F30: 0
